flockwave/gateway/__init__.py
flockwave/gateway/app.py
flockwave/gateway/asgi_app.py
flockwave/gateway/config.py
flockwave/gateway/errors.py
flockwave/gateway/launcher.py
flockwave/gateway/logger.py
flockwave/gateway/version.py
flockwave/gateway/workers.py
flockwave/proxy/__init__.py
flockwave/proxy/app.py
flockwave/proxy/config.py
flockwave/proxy/launcher.py
flockwave/proxy/logger.py
flockwave/proxy/version.py
flockwave/server/__init__.py
flockwave/server/__main__.py
flockwave/server/app.py
flockwave/server/comm.py
flockwave/server/command_handlers/__init__.py
flockwave/server/command_handlers/color.py
flockwave/server/command_handlers/parameters.py
flockwave/server/command_handlers/version.py
flockwave/server/commands.py
flockwave/server/config.py
flockwave/server/errors.py
flockwave/server/ext/__init__.py
flockwave/server/ext/auth.py
flockwave/server/ext/auth_basic.py
flockwave/server/ext/auth_jwt.py
flockwave/server/ext/auto_shutdown.py
flockwave/server/ext/base.py
flockwave/server/ext/beacon/__init__.py
flockwave/server/ext/beacon/extension.py
flockwave/server/ext/beacon/model.py
flockwave/server/ext/clocks.py
flockwave/server/ext/connection_limits.py
flockwave/server/ext/console_status.py
flockwave/server/ext/crazyflie/__init__.py
flockwave/server/ext/crazyflie/connection.py
flockwave/server/ext/crazyflie/crtp_extensions.py
flockwave/server/ext/crazyflie/driver.py
flockwave/server/ext/crazyflie/extension.py
flockwave/server/ext/crazyflie/fence.py
flockwave/server/ext/crazyflie/led_lights.py
flockwave/server/ext/crazyflie/math.py
flockwave/server/ext/crazyflie/scanning.py
flockwave/server/ext/crazyflie/trajectory.py
flockwave/server/ext/debug/__init__.py
flockwave/server/ext/debug/extension.py
flockwave/server/ext/debug/server.py
flockwave/server/ext/ext_manager.py
flockwave/server/ext/fd.py
flockwave/server/ext/frontend/__init__.py
flockwave/server/ext/frontend/extension.py
flockwave/server/ext/frontend/static/style.css
flockwave_server-2.0.0.dist-info/entry_points.txt
flockwave_server-2.0.0.dist-info/LICENSE.txt
flockwave_server-2.0.0.dist-info/WHEEL
flockwave_server-2.0.0.dist-info/METADATA
flockwave_server-2.0.0.dist-info/RECORD
