Metadata-Version: 2.1
Name: flockwave-server
Version: 2.0.0
Summary: Skybrush server component
License: GPL-3.0-or-later
Author: Tamas Nepusz
Author-email: tamas@collmot.com
Requires-Python: >=3.8,<4.0
Classifier: License :: OSI Approved :: GNU General Public License v3 or later (GPLv3+)
Classifier: Programming Language :: Python :: 3
Classifier: Programming Language :: Python :: 3.10
Classifier: Programming Language :: Python :: 3.8
Classifier: Programming Language :: Python :: 3.9
Provides-Extra: all
Provides-Extra: collmot
Provides-Extra: pro
Requires-Dist: adrenaline (>=1.0.0,<2.0.0)
Requires-Dist: aio-usb-hotplug (>=5.0.0,<6.0.0)
Requires-Dist: aiocflib (>=2.5.2,<3.0.0)
Requires-Dist: appdirs (>=1.4.4,<2.0.0)
Requires-Dist: bidict (>=0.19.0)
Requires-Dist: blinker (>=1.4,<2.0)
Requires-Dist: click (>=8.0.0,<9.0.0)
Requires-Dist: colour (>=0.1.5)
Requires-Dist: compose (>=1.1.1,<2.0.0)
Requires-Dist: crcmod (>=1.7,<2.0)
Requires-Dist: flockwave-app-framework[daemon] (>=2.4.1,<3.0.0)
Requires-Dist: flockwave-async (>=1.3.0,<2.0.0)
Requires-Dist: flockwave-conn[rpc,serial] (>=5.0.0,<6.0.0)
Requires-Dist: flockwave-ext (>=1.14.3,<2.0.0)
Requires-Dist: flockwave-gps (>=2.2.0,<3.0.0)
Requires-Dist: flockwave-logger (>=1.8.0,<2.0.0)
Requires-Dist: flockwave-mavlink (>=0.1.0)
Requires-Dist: flockwave-net[async] (>=3.0.1,<4.0.0)
Requires-Dist: flockwave-parsers (>=2.0.1,<3.0.0)
Requires-Dist: flockwave-spec (>=1.61.0,<2.0.0)
Requires-Dist: httpx (>=0.18.2)
Requires-Dist: hypercorn[trio] (>=0.10.1)
Requires-Dist: igrf-model (>=1.1.1,<2.0.0)
Requires-Dist: jsonschema (>=4.0.3,<5.0.0)
Requires-Dist: msgpack (>=1.0.0,<2.0.0)
Requires-Dist: passlib[bcrypt] (>=1.7.2,<2.0.0)
Requires-Dist: pyjwt (>=1.7.1,<2.0.0)
Requires-Dist: pyledctrl (>=4.0.0,<5.0.0)
Requires-Dist: pynmea2 (>=1.15.0,<2.0.0)
Requires-Dist: pyserial (>=3.4,<4.0)
Requires-Dist: python-baseconv (>=1.2.2,<2.0.0)
Requires-Dist: python-dotenv (>=0.14.0)
Requires-Dist: quart (>=0.16.0)
Requires-Dist: quart-trio (>=0.9.0)
Requires-Dist: skybrush-ext-dock (>=1.0.0,<2.0.0); extra == "all" or extra == "collmot"
Requires-Dist: skybrush-ext-flockctrl (>=1.0.1,<2.0.0); extra == "all" or extra == "collmot"
Requires-Dist: skybrush-ext-sidekick (>=1.0.0,<2.0.0); extra == "all" or extra == "pro"
Requires-Dist: skybrush-ext-timecode (>=1.0.0,<2.0.0); extra == "all" or extra == "collmot" or extra == "pro"
Requires-Dist: trio (>=0.20.0)
Requires-Dist: trio-util (>=0.5.0)
